{
  "name": "Storage Accessor",
  "icon": "occultism:storage_remote",
  "category": "rituals/crafting",
  "sortnum": 24,
  "pages": [
    {
      "type": "spotlight",
      "item": "occultism:storage_remote",
      "text": "Это $(item)Storage Remote$() (Удаленное хранилище)можно связать с $(item)Storage Actuator$() (Приводом для хранения). Этот $(thing)Djinni$() привязанный к аксессуару, тогда сможет получить доступ к предметам с Привода для храненияя даже из других измерений."
    },
    {
      "type": "summoning",
      "heading": "Infusion",
      "pentacle": "$(l:pentacles/craft_djinni)Strigeor's Higher Binding$(/l)",
      "activation_item": "occultism:book_of_binding_bound_djinni",
      "ingredients": "$(li)1x $(item)Inert Storage Remote $()$(li)2x $(item)Ender Pearl $()$(li)1x $(item)Nether Quartz $()"
    }
  ]
}