{
  "name": "Círculo Aviar",
  "icon": "occultism:textures/gui/book/pentagram_rose.png",
  "category": "occultism:pentacles",
  "sortnum": 10,
  "pages": [
    {
      "type": "text",
      "text": "$(bold)Objetivo:$() Invocar Foliot $(br2) Considerado el pentáculo más simple, $(thing)Círculo de Aviar$() es fácil de preparar, pero otorga un poder de vinculación y protección mínimo para el invocador. $(br2)Sólo los más débiles y fácilmente doblegables $(thing)Foliot$() pueden ser invocados en rituales con este pentáculo."},
    {
      "type": "multiblock",
      "name": "",
      "multiblock_id": "occultism:pentacle.summon_foliot"
    },
    {
      "type": "text",
      "title": "Usos",
      "text": "$(li)$(l:rituals/summoning/summon_crusher)Foliot Triturador$(/l)$()$(li)$(l:rituals/summoning/summon_lumberjack)Foliot Leñador$(/l)$()$(li)$(l:rituals/summoning/summon_transport_items)Foliot Transportador$(/l)$()$(li)$(l:rituals/summoning/summon_cleaner)Foliot Conserje$(/l)$()$(li)$(l:rituals/summoning/summon_otherstone_trader)Comerciante de Piedra del Otro Lado$(/l)$()$(li)$(l:rituals/summoning/summon_otherworld_sapling_trader)Comerciante de brotes del Otro Lado$(/l)$()"}
  ]
}