{
  "name": "Familiar Ring",
  "icon": "occultism:familiar_ring",
  "category": "occultism:rituals/crafting",
  "sortnum": 13,
  "pages": [
    {
      "type": "spotlight",
      "item": "occultism:familiar_ring",
      "text": "Los anillos familiares consisten de una gema de alma montada en un anillo que contiene a un Djinni. El Djinni del anillo permite al familiar capturado en la gema de alma aplicar efectos al poseedor."},
    {
      "type": "text",
      "title": "Uso",
      "text": "Para utilizar un anillo familiar, captura a un familiar invocado (y domado) y equípate el anillo para utilizar los efectos que el familiar otorga. Cuando se libera al espíritu del anillo, reconocerá a la persona que lo libera como su nuevo amo."},
    {
      "type": "occultism:ritual",
      "recipe": "occultism:ritual/craft_familiar_ring"
    }
  ]
}