{
  "type": "occultism:crushing",
  "conditions": [
    {
      "type": "forge:not",
      "value": {
        "type": "forge:tag_empty",
        "tag": "forge:dusts/iesnium"
      }
    },
    {
      "type": "forge:not",
      "value": {
        "type": "forge:tag_empty",
        "tag": "forge:ingots/iesnium"
      }
    }
  ],
  "crushing_time": 200,
  "ignore_crushing_multiplier": true,
  "ingredient": {
    "tag": "forge:ingots/iesnium"
  },
  "result": {
    "count": 1,
    "tag": "forge:dusts/iesnium"
  }
}