{
  "display": {
    "icon": {
      "id": "occultism:chalk_purple"
    },
    "title": {"translate": "advancements.occultism.chalks.purple.title"},
    "description": {"color":"green","translate":"advancements.occultism.chalks.purple.description"},
    "show_toast": true,
    "announce_to_chat": false
  },
  "parent": "occultism:chalks/yellow",
  "criteria": {
    "chalk_white": {
      "trigger": "minecraft:inventory_changed",
      "conditions": {
        "items": [
          {
            "items": [
              "occultism:chalk_purple"
            ]
          }
        ]
      }
    }
  }
}
