{
  "background_u_index": 0,
  "background_v_index": 0,
  "category": "occultism:rituals",
  "category_to_open": "occultism:familiar_rituals",
  "condition": {
    "type": "modonomicon:true"
  },
  "description": "",
  "hide_while_locked": false,
  "icon": "occultism:textures/gui/book/parrot.png",
  "name": "book.occultism.dictionary_of_spirits.rituals.familiar_rituals.name",
  "parents": [
    {
      "draw_arrow": true,
      "entry": "occultism:rituals/sacrifice",
      "line_enabled": true,
      "line_reversed": false
    }
  ],
  "x": 7,
  "y": 2
}