{
  "parent": "minecraft:recipes/root",
  "criteria": {
    "has_iesnium_block": {
      "conditions": {
        "items": [
          {
            "tag": "forge:storage_blocks/iesnium"
          }
        ]
      },
      "trigger": "minecraft:inventory_changed"
    },
    "has_the_recipe": {
      "conditions": {
        "recipe": "occultism:crafting/iesnium_ingot_from_block"
      },
      "trigger": "minecraft:recipe_unlocked"
    }
  },
  "requirements": [
    [
      "has_iesnium_block",
      "has_the_recipe"
    ]
  ],
  "rewards": {
    "recipes": [
      "occultism:crafting/iesnium_ingot_from_block"
    ]
  },
  "sends_telemetry_event": false
}